{
  "asOf": "2026-03-09 20:00 Asia/Shanghai｜版本号(v20260309-2000)｜生成时间(2026-03-09 20:00 Asia/Shanghai)｜commit(6710806)",
  "version": "v20260309-2000",
  "generatedAt": "2026-03-09 20:00 Asia/Shanghai",
  "keywords": [
    "并购",
    "先进封装",
    "半导体材料",
    "资金分化",
    "国产替代"
  ],
  "key_data": [
    {
      "metric": "观察窗口",
      "value": "最近6小时（14:00-20:00）"
    },
    {
      "metric": "增量突发",
      "value": "5条（去重后）"
    },
    {
      "metric": "国内媒体来源",
      "value": "5/5"
    }
  ],
  "items": [
    {
      "region": "domestic",
      "title": "【置顶】新劲刚拟收购高至科技控股权，切入飞行器关键部组件赛道",
      "source": "36氪",
      "published": "2026-03-09 18:10",
      "url": "https://36kr.com/newsflashes",
      "heat": 95,
      "summary": "<ul><li>36氪快讯披露，新劲刚正在筹划收购湖南高至科技控股权，交易价格将以评估值为参考协商确定。</li><li>标的公司聚焦飞行器关键部组件，若交易落地将强化公司在高可靠电子与特种应用方向布局。</li></ul>",
      "insights": [
        "并购型外延扩张在高端电子产业链升温，资金更关注并表后的订单兑现能力。"
      ],
      "actions": [
        "跟踪后续交易对价、业绩承诺与监管进展，评估对供应链协同的实质贡献。"
      ],
      "tags": [
        "并购",
        "重大事项"
      ]
    },
    {
      "region": "domestic",
      "title": "半导体板块拉升，江化微涨停、蓝箭电子等走强",
      "source": "证券时报",
      "published": "2026-03-09 16:40",
      "url": "https://www.stcn.com/article/detail/3601574.html",
      "heat": 91,
      "summary": "<ul><li>证券时报盘中跟踪显示，半导体板块出现拉升，设备与设计细分同步走强。</li><li>市场交易主线仍围绕AI算力和先进制程扩产预期展开。</li></ul>",
      "insights": [
        "板块弹性仍在，但个股分化加剧，趋势行情更依赖业绩与订单验证。"
      ],
      "actions": [
        "重点观察设备龙头与上游材料的量价信号，避免情绪化追涨。"
      ],
      "tags": [
        "盘面",
        "设备"
      ]
    },
    {
      "region": "domestic",
      "title": "半导体板块再走强，气派科技20%涨停、普冉股份创新高",
      "source": "证券时报",
      "published": "2026-03-09 17:05",
      "url": "https://www.stcn.com/article/detail/3615979.html",
      "heat": 89,
      "summary": "<ul><li>证券时报报道，半导体板块继续活跃，先进封装与存储链条表现突出。</li><li>市场对涨价传导与AI需求延续的预期保持敏感。</li></ul>",
      "insights": [
        "从存储到封测再到CPU的价格传导，正在重塑产业链利润分配。"
      ],
      "actions": [
        "跟踪封测厂稼动率与价格执行节奏，优先筛选现金流改善公司。"
      ],
      "tags": [
        "先进封装",
        "存储"
      ]
    },
    {
      "region": "domestic",
      "title": "半导体材料方向活跃：碳化硅、氮化镓关注度上升",
      "source": "证券时报",
      "published": "2026-03-09 18:25",
      "url": "https://www.stcn.com/article/detail/3598441.html",
      "heat": 86,
      "summary": "<ul><li>证券时报梳理显示，半导体材料方向受国产替代与第三代半导体应用扩展驱动走强。</li><li>碳化硅/氮化镓在车规与高功率场景的渗透率持续提升。</li></ul>",
      "insights": [
        "材料端成为中长期阿尔法来源，技术门槛与客户认证周期决定估值上限。"
      ],
      "actions": [
        "持续跟踪8英寸SiC衬底与外延产能进展、车规导入节奏。"
      ],
      "tags": [
        "第三代半导体",
        "材料"
      ]
    },
    {
      "region": "domestic",
      "title": "融资资金分化：存储获抢筹，部分半导体个股遭净偿还",
      "source": "证券时报",
      "published": "2026-03-09 19:00",
      "url": "https://www.stcn.com/article/detail/3666520.html",
      "heat": 84,
      "summary": "<ul><li>证券时报数据宝显示，电子板块融资交易分化，存储链条资金关注度较高。</li><li>高波动环境下，半导体内部出现“景气主线+高位回撤”并行格局。</li></ul>",
      "insights": [
        "资金风格由普涨切换为结构化博弈，龙头与次龙头定价差扩大。"
      ],
      "actions": [
        "关注融资余额边际变化与成交额匹配度，防范高换手回撤风险。"
      ],
      "tags": [
        "资金流",
        "存储"
      ]
    }
  ],
  "glossary": [
    {
      "term": "KGD（Known Good Die）",
      "desc": "已知良率裸芯片，常用于多芯粒/封装集成，能降低封装后失效率。"
    },
    {
      "term": "稼动率（Utilization Rate）",
      "desc": "产线实际产出与理论产能的比值，是判断景气度与议价能力的先行指标。"
    }
  ],
  "footer": "版本号(v20260309-2000)｜生成时间(2026-03-09 20:00 Asia/Shanghai)｜commit(6710806)"
}